medium_speech/MediumToSpeech.py
medium_speech/__init__.py
medium_speech/__version__.py
medium_speech-0.1.3.data/scripts/play_medium_post.py
medium_speech-0.1.3.dist-info/LICENSE
medium_speech-0.1.3.dist-info/METADATA
medium_speech-0.1.3.dist-info/WHEEL
medium_speech-0.1.3.dist-info/top_level.txt
medium_speech-0.1.3.dist-info/RECORD
