Metadata-Version: 2.1
Name: medium-speech
Version: 0.1.3
Summary: Medium posts as Markdown to Speech.
Home-page: https://github.com/mmphego/medium-to-speech
Author: Mpho Mphego
Author-email: mpho112@gmail.com
License: MIT
Project-URL: Bug Reports, https://github.com/mmphego/markdown-to-speech//issues
Project-URL: Source, https://github.com/mmphego/markdown-to-speech/
Project-URL: Say Thanks!, https://saythanks.io/to/mmphego
Project-URL: AboutMe, https://blog.mphomphego.co.za/aboutme
Keywords: medium markdown docker-py text-to-speech
Platform: UNKNOWN
Classifier: Development Status :: 3 - Alpha
Classifier: Intended Audience :: Developers
Classifier: Topic :: Software Development :: Build Tools
Classifier: License :: OSI Approved :: MIT License
Classifier: Programming Language :: Python :: 3.6
Classifier: Programming Language :: Python :: 3.7
Requires-Python: ~=3.6
Requires-Dist: argcomplete
Requires-Dist: coloredlogs
Requires-Dist: docker[tls]
Requires-Dist: gTTS
Requires-Dist: Markdown
Provides-Extra: testing
Requires-Dist: coverage ; extra == 'testing'
Requires-Dist: flake8 ; extra == 'testing'
Requires-Dist: mock ; extra == 'testing'
Requires-Dist: nose ; extra == 'testing'
Requires-Dist: pytest ; extra == 'testing'
